lifescale/__init__.py
lifescale/command_line/__init__.py
lifescale/command_line/command_line.py
lifescale/gui/MainWindow.py
lifescale/gui/__init__.py
lifescale/gui/dialog_about.py
lifescale/gui/gui_main.py
lifescale/gui/masses_model.py
lifescale/gui/panel_metadata_model.py
lifescale/gui/resources.py
lifescale/gui/sample_summary_model.py
lifescale/models/__init__.py
lifescale/models/ls_data.py
lifescale/scripts/__init__.py
lifescale/scripts/ls2csv.py
lifescale/scripts/run_gui.py
lifescale_utils-0.0.7.dist-info/LICENSE
lifescale_utils-0.0.7.dist-info/METADATA
lifescale_utils-0.0.7.dist-info/WHEEL
lifescale_utils-0.0.7.dist-info/entry_points.txt
lifescale_utils-0.0.7.dist-info/top_level.txt
lifescale_utils-0.0.7.dist-info/zip-safe
lifescale_utils-0.0.7.dist-info/RECORD
