Metadata-Version: 2.1
Name: lifescale-utils
Version: 0.0.7
Summary: Lifescale utility software.
Home-page: https://gitlab.com/hellerdev/lifescale_utils
Author: Andreas Hellerschmied
Author-email: heller182@gmx.at
License: GNU GPLv3
Keywords: Lifescale
Classifier: License :: OSI Approved :: GNU General Public License (GPL)
Classifier: Programming Language :: Python :: 3
Requires-Python: <4,>=3.6
License-File: LICENSE
Requires-Dist: numpy
Requires-Dist: pandas
Requires-Dist: openpyxl
Requires-Dist: PyQt6
Requires-Dist: pyqtgraph
